buddhi/core/document_utils.py
buddhi/core/utils.py
buddhi/main.py
buddhi/services/generation_service.py
buddhi/services/indexing_service.py
buddhi/services/prompt_service.py
buddhi/services/retrieval_service.py
buddhi-0.1.0.dist-info/LICENSE
buddhi-0.1.0.dist-info/METADATA
buddhi-0.1.0.dist-info/WHEEL
buddhi-0.1.0.dist-info/RECORD
