Metadata-Version: 2.3
Name: buddhi
Version: 0.1.0
Summary: Buddhi AI is an intelligent, AI-powered career assistant designed to help job seekers navigate every aspect of their job search and professional growth. Whether you are looking for your first job, a career switch, or upskilling opportunities, Buddhi AI provides personalized recommendations, smart job matching, resume assistance, interview preparation, and career guidance—all in one place.
License: GNU GENERAL PUBLIC LICENSE
Keywords: AI agent,python,package,buddhi,career assistant,job search,professional growth,job matching,resume assistance,interview preparation,career guidance
Author: balajihambeere
Author-email: balaji.hambere@gmail.com
Requires-Python: >=3.12,<4.0
Classifier: Programming Language :: Python :: 3
Classifier: License :: OSI Approved :: GNU General Public License v3 (GPLv3)
Classifier: Operating System :: OS Independent
Requires-Dist: langchain (>=0.3.19,<0.4.0)
Requires-Dist: langchain-community (>=0.3.18,<0.4.0)
Requires-Dist: langchain-milvus (>=0.1.8,<0.2.0)
Requires-Dist: langchain-openai (>=0.3.7,<0.4.0)
Requires-Dist: langchain-postgres (>=0.0.13,<0.0.14)
Requires-Dist: langchain-text-splitters (>=0.3.6,<0.4.0)
Requires-Dist: python-dotenv (>=1.0.1,<2.0.0)
Project-URL: Homepage, https://github.com/zudyog/buddhi
Project-URL: Issues, https://github.com/zudyog/buddhi/issues
Project-URL: Repository, https://github.com/zudyog/buddhi
